Workbook

Sheet Questions
B1: Union_Europeenne | C1: Egalite_Hommes_Femmes | D1: Environnement | E1: Alimentation | F1: Etats_Unis | G1: Racisme | H1: Cinema | I1: Energie | J1: Politique_Industrielle | K1: Lutte_des_classes | L1: Justice | M1: Violences_Policières | N1: Salaires | O1: Religion | P1: Inegalites_sociales | Q1: Finances | R1: Nucleaire | S1: Energies_Renouvelables | T1: Histoire | U1: Patrimoine | V1: Devoir_de_memoire | W1: Musique | X1: Ordre_Moral | Y1: Secularisation | Z1: LGBTIQ | AA1: Politique_Etrangère | AB1: Enseignement | AC1: Internet | AD1: Democratie | AE1: Droits_des_minorites | AF1: Interventionnisme | AG1: Laisser_faire | AH1: Liberalisme_economique | AI1: Souverainisme | AJ1: Mondialisation | AK1: Liberalisation_des_moeurs | AL1: Liberte_d_expression | AM1: Education_sexuelle | AN1: Economie_circulaire | AO1: Libertarisme
A2: Pour ou contre l'Union Européenne | B2: 1
A3: Pour ou contre le César du meilleur film attribué à J'Accuse de Roman Polanski | C3: -0.4 | H3: 0.4 | L3: -0.1 | AL3: 0.2
A4: Pour ou contre le fait pour un état d'intervenir militairement hors de ses frontières | B4: 0.1 | F4: 0.1 | L4: 0.1 | AA4: 0.7
A5: Pour ou contre la reconstruction à l'identique de Notre-Dame-de-Paris | O5: 0.2 | T5: 0.1 | U5: 0.5 | V5: 0.1 | X5: 0.1
A6: Pour ou contre Booba | W6: 0.8 | X6: 0.2
A7: Pour ou contre le nucléaire | D7: 0.1 | I7: 0.1 | J7: 0.05 | R7: 0.85 | S7: -0.2 | U7: 0.05 | AA7: 0.05
A8: Pour ou contre l'ouverture de la PMA aux couples de lesbiennes | C8: 0.1 | O8: -0.2 | X8: -0.2 | Y8: 0.2 | Z8: 1 | AE8: 0.1
A9: Pour ou contre les espaces interdits aux hommes | C9: 0.8 | Z9: 0.1 | AE9: 0.1
A10: Pour ou contre Amazon | B10: -0.1 | D10: -0.1 | F10: 0.2 | AF10: -0.1 | AG10: 0.3 | AH10: 0.3 | AI10: -0.5 | AJ10: 0.8
A11: Pour ou contre les préliminaires | C11: 0.2 | O11: -0.1 | X11: -0.2 | Z11: 0.1 | AK11: 0.3 | AL11: 0.1 | AM11: 0.6
A12: Pour ou contre la collapsologie | D12: 0.2 | E12: 0.2 | I12: 0.2 | S12: 0.2 | AD12: 0.1 | AH12: 0.1 | AI12: 0.2 | AJ12: -0.2
A13: Pour ou contre le survivalisme | L13: 0.2 | AI13: 0.6 | AJ13: -0.2 | AO13: 0.4
A14: Pour ou contre les parcs naturels | D14: 0.8 | U14: 0.2 | AD14: 0.1 | AO14: -0.1
A15: Pour ou contre le droit de tuer des loups | D15: -0.5 | E15: 0.4 | L15: -0.1 | U15: -0.1 | X15: 0.3 | AO15: 1
A16: Pour ou contre le droit à l'autogestion pour les communautés indigènes jusqu'au meurtre | T16: 0.1 | U16: 0.1 | AE16: 0.8 | AF16: -0.1 | AJ16: -0.5 | AK16: 0.1 | AO16: 0.5
A17: Pour ou contre le revenu universel | K17: 0.7 | N17: 0.5 | Q17: 0.5 | AF17: 0.5 | AG17: -0.2 | AH17: -0.8 | AJ17: -0.4 | AO17: -0.8
A18: Pour ou contre les pronoms non genrés | C18: 0.4 | O18: -0.1 | X18: -0.1 | Z18: 0.4 | AE18: 0.4
A19: Pour ou contre le droit pour l'Etat de faire fermer une école privée hors contrat | L19: 0.5 | O19: -0.8 | X19: -0.2 | Y19: 0.7 | AB19: 1 | AF19: 0.5 | AH19: -0.1 | AL19: -0.1 | AO19: -0.5
A20: Pour ou contre le fait de faire chanter la Marseillaise à des élèves | B20: -0.2 | T20: 0.2 | U20: 0.2 | X20: 0.5 | AI20: 0.5 | AJ20: -0.2
A21: Pour ou contre l'ajout d'une contextualisation obligatoire avant le visionnage d'oeuvres cinématographiques | C21: 0.6 | G21: 0.6 | H21: -0.4 | U21: -0.1 | V21: -0.1 | W21: -0.4 | AB21: 0.4 | AD21: 0.2 | AE21: 0.6 | AL21: -0.4
A22: Pour ou contre la création d'un monopole public de l'énergie | D22: 0.2 | I22: 0.5 | J22: 0.2 | R22: 0.4 | S22: -0.1 | AF22: 0.2 | AG22: -0.2 | AH22: -0.2 | AI22: 0.2 | AJ22: -0.2
A23: Pour ou contre la vente d'armes à des états en guerre, ouverte ou à distance (ex : l'Arabie Saoudite) | J23: 0.1 | Q23: 0.1 | AA23: 0.8 | AD23: -0.2 | AH23: 0.2
A24: Pour ou contre la vente d'armes à des états non démocratiques (ex : l'Egypte) | J24: 0.1 | Q24: 0.1 | AA24: 0.8 | AD24: -0.3 | AH24: 0.3
A25: Pour ou contre le printemps arabe | L25: 0.2 | X25: 0.1 | AA25: 0.1 | AI25: 0.3 | AL25: 0.3
A26: Pour ou contre les repas halal à la cantine | E26: -0.1 | G26: 0.5 | O26: 0.5 | AD26: 0.1 | AE26: 0.5
A27: Pour ou contre les écoles privées | K27: -0.4 | P27: -0.6 | AB27: 0.4 | AG27: 0.3 | AO27: 0.5
A28: Pour ou contre la taxation des GAFAM
A29: Pour ou contre le démantèlement des GAFAM
A30: Pour ou contre la prise en compte du vote blanc dans les scores électoraux
A31: Pour ou contre la démocratie participative
A32: Pour ou contre la mise en oeuvre de nouvelles méthodes de vote
A33: Pour ou contre le vote par correspondance
A34: Pour ou contre l'ouverture des magasins le dimanche
A35: Pour ou contre l'enseignement de l'arabe à l'école publique
A36: Pour ou contre la légalisation des psychotropes au niveau du tabac et de l'alcool
A37: Pour ou contre le Royaume-Uni dans l'Union Européenne
A38: Pour ou contre un ministère dédié à l'identité nationale
A39: Pour ou contre la mise en place d'un impôt sur la fortune
... A195: Pour ou contre les parisiens

Sheet ThèmesDimensions
A1: Dimensions/Thèmes
A2: Union Européenne
A3: Egalité Hommes/Femmes
A4: Environnement
A5: Alimentation
A6: Etats Unis
A7: Racisme
A8: Cinéma
A9: Energie
A10: Politique Industrielle
A11: Lutte des classes
A12: Justice
... A30: Démocratie

Sheet Agregation
B1: Liberalisme | C1: Wokisme | D1: Nationalisme | E1: Boboisme
A2: Pour ou contre l'Union Européenne | B2: =Questions!B2+Questions!Q2+Questions!AO2+Questions!AJ2+Questions!AH2+Questions!AG2+Questions!AC2 -> 1 | C2: =Questions!C2+Questions!G2+Questions!M2-Questions!O2-Questions!T2-Questions!X2+Questions!Z2+Questions!AM2-Questions!AL2+Questions!AK2 -> 0 | D2: =-Questions!B2-Questions!F2+Questions!J2-Questions!M2+Questions!R2+Questions!T2+Questions!U2+Questions!V2+Questions!X2+Questions!AA2-Questions!AE2+Questions!AF2-Questions!AG2-Questions!AH2+Questions!AI2-Questions!AJ2-Questions!AO2 -> -1 | E2: =Questions!D2+Questions!E2+Questions!H2+Questions!G2+Questions!L2+Questions!K2+Questions!N2-Questions!O2+Questions!P2+Questions!S2-Questions!R2+Questions!Z2+Questions!AB2+Questions!AD2+Questions!AE2+Questions!AG2+Questions!AN2 -> 0
A3: Pour ou contre le César du meilleur film attribué à J'Accuse de Roman Polanski | B3: =Questions!B3+Questions!Q3+Questions!AO3+Questions!AJ3+Questions!AH3+Questions!AG3+Questions!AC3 -> 0 | C3: =Questions!C3+Questions!G3+Questions!M3-Questions!O3-Questions!T3-Questions!X3+Questions!Z3+Questions!AM3-Questions!AL3+Questions!AK3 -> -0.6 | D3: =-Questions!B3-Questions!F3+Questions!J3-Questions!M3+Questions!R3+Questions!T3+Questions!U3+Questions!V3+Questions!X3+Questions!AA3-Questions!AE3+Questions!AF3-Questions!AG3-Questions!AH3+Questions!AI3-Questions!AJ3-Questions!AO3 -> 0 | E3: =Questions!D3+Questions!E3+Questions!H3+Questions!G3+Questions!L3+Questions!K3+Questions!N3-Questions!O3+Questions!P3+Questions!S3-Questions!R3+Questions!Z3+Questions!AB3+Questions!AD3+Questions!AE3+Questions!AG3+Questions!AN3 -> 0.3
A4: Pour ou contre le fait pour un état d'intervenir militairement hors de ses frontières | B4: =Questions!B4+Questions!Q4+Questions!AO4+Questions!AJ4+Questions!AH4+Questions!AG4+Questions!AC4 -> 0.1 | C4: =Questions!C4+Questions!G4+Questions!M4-Questions!O4-Questions!T4-Questions!X4+Questions!Z4+Questions!AM4-Questions!AL4+Questions!AK4 -> 0 | D4: =-Questions!B4-Questions!F4+Questions!J4-Questions!M4+Questions!R4+Questions!T4+Questions!U4+Questions!V4+Questions!X4+Questions!AA4-Questions!AE4+Questions!AF4-Questions!AG4-Questions!AH4+Questions!AI4-Questions!AJ4-Questions!AO4 -> 0.5 | E4: =Questions!D4+Questions!E4+Questions!H4+Questions!G4+Questions!L4+Questions!K4+Questions!N4-Questions!O4+Questions!P4+Questions!S4-Questions!R4+Questions!Z4+Questions!AB4+Questions!AD4+Questions!AE4+Questions!AG4+Questions!AN4 -> 0.1
A5: Pour ou contre la reconstruction à l'identique de Notre-Dame-de-Paris | B5: =Questions!B5+Questions!Q5+Questions!AO5+Questions!AJ5+Questions!AH5+Questions!AG5+Questions!AC5 -> 0 | C5: =Questions!C5+Questions!G5+Questions!M5-Questions!O5-Questions!T5-Questions!X5+Questions!Z5+Questions!AM5-Questions!AL5+Questions!AK5 -> -0.4 | D5: =-Questions!B5-Questions!F5+Questions!J5-Questions!M5+Questions!R5+Questions!T5+Questions!U5+Questions!V5+Questions!X5+Questions!AA5-Questions!AE5+Questions!AF5-Questions!AG5-Questions!AH5+Questions!AI5-Questions!AJ5-Questions!AO5 -> 0.8 | E5: =Questions!D5+Questions!E5+Questions!H5+Questions!G5+Questions!L5+Questions!K5+Questions!N5-Questions!O5+Questions!P5+Questions!S5-Questions!R5+Questions!Z5+Questions!AB5+Questions!AD5+Questions!AE5+Questions!AG5+Questions!AN5 -> -0.2
A6: Pour ou contre Booba | B6: =Questions!B6+Questions!Q6+Questions!AO6+Questions!AJ6+Questions!AH6+Questions!AG6+Questions!AC6 -> 0 | C6: =Questions!C6+Questions!G6+Questions!M6-Questions!O6-Questions!T6-Questions!X6+Questions!Z6+Questions!AM6-Questions!AL6+Questions!AK6 -> -0.2 | D6: =-Questions!B6-Questions!F6+Questions!J6-Questions!M6+Questions!R6+Questions!T6+Questions!U6+Questions!V6+Questions!X6+Questions!AA6-Questions!AE6+Questions!AF6-Questions!AG6-Questions!AH6+Questions!AI6-Questions!AJ6-Questions!AO6 -> 0.2 | E6: =Questions!D6+Questions!E6+Questions!H6+Questions!G6+Questions!L6+Questions!K6+Questions!N6-Questions!O6+Questions!P6+Questions!S6-Questions!R6+Questions!Z6+Questions!AB6+Questions!AD6+Questions!AE6+Questions!AG6+Questions!AN6 -> 0
A7: Pour ou contre le nucléaire | B7: =Questions!B7+Questions!Q7+Questions!AO7+Questions!AJ7+Questions!AH7+Questions!AG7+Questions!AC7 -> 0 | C7: =Questions!C7+Questions!G7+Questions!M7-Questions!O7-Questions!T7-Questions!X7+Questions!Z7+Questions!AM7-Questions!AL7+Questions!AK7 -> 0 | D7: =-Questions!B7-Questions!F7+Questions!J7-Questions!M7+Questions!R7+Questions!T7+Questions!U7+Questions!V7+Questions!X7+Questions!AA7-Questions!AE7+Questions!AF7-Questions!AG7-Questions!AH7+Questions!AI7-Questions!AJ7-Questions!AO7 -> 1 | E7: =Questions!D7+Questions!E7+Questions!H7+Questions!G7+Questions!L7+Questions!K7+Questions!N7-Questions!O7+Questions!P7+Questions!S7-Questions!R7+Questions!Z7+Questions!AB7+Questions!AD7+Questions!AE7+Questions!AG7+Questions!AN7 -> -0.95
A8: Pour ou contre l'ouverture de la PMA aux couples de lesbiennes | B8: =Questions!B8+Questions!Q8+Questions!AO8+Questions!AJ8+Questions!AH8+Questions!AG8+Questions!AC8 -> 0 | C8: =Questions!C8+Questions!G8+Questions!M8-Questions!O8-Questions!T8-Questions!X8+Questions!Z8+Questions!AM8-Questions!AL8+Questions!AK8 -> 1.5 | D8: =-Questions!B8-Questions!F8+Questions!J8-Questions!M8+Questions!R8+Questions!T8+Questions!U8+Questions!V8+Questions!X8+Questions!AA8-Questions!AE8+Questions!AF8-Questions!AG8-Questions!AH8+Questions!AI8-Questions!AJ8-Questions!AO8 -> -0.3 | E8: =Questions!D8+Questions!E8+Questions!H8+Questions!G8+Questions!L8+Questions!K8+Questions!N8-Questions!O8+Questions!P8+Questions!S8-Questions!R8+Questions!Z8+Questions!AB8+Questions!AD8+Questions!AE8+Questions!AG8+Questions!AN8 -> 1.3
A9: Pour ou contre les espaces interdits aux hommes | B9: =Questions!B9+Questions!Q9+Questions!AO9+Questions!AJ9+Questions!AH9+Questions!AG9+Questions!AC9 -> 0 | C9: =Questions!C9+Questions!G9+Questions!M9-Questions!O9-Questions!T9-Questions!X9+Questions!Z9+Questions!AM9-Questions!AL9+Questions!AK9 -> 0.9 | D9: =-Questions!B9-Questions!F9+Questions!J9-Questions!M9+Questions!R9+Questions!T9+Questions!U9+Questions!V9+Questions!X9+Questions!AA9-Questions!AE9+Questions!AF9-Questions!AG9-Questions!AH9+Questions!AI9-Questions!AJ9-Questions!AO9 -> -0.1 | E9: =Questions!D9+Questions!E9+Questions!H9+Questions!G9+Questions!L9+Questions!K9+Questions!N9-Questions!O9+Questions!P9+Questions!S9-Questions!R9+Questions!Z9+Questions!AB9+Questions!AD9+Questions!AE9+Questions!AG9+Questions!AN9 -> 0.2
A10: Pour ou contre Amazon | B10: =Questions!B10+Questions!Q10+Questions!AO10+Questions!AJ10+Questions!AH10+Questions!AG10+Questions!AC10 -> 1.3 | C10: =Questions!C10+Questions!G10+Questions!M10-Questions!O10-Questions!T10-Questions!X10+Questions!Z10+Questions!AM10-Questions!AL10+Questions!AK10 -> 0 | D10: =-Questions!B10-Questions!F10+Questions!J10-Questions!M10+Questions!R10+Questions!T10+Questions!U10+Questions!V10+Questions!X10+Questions!AA10-Questions!AE10+Questions!AF10-Questions!AG10-Questions!AH10+Questions!AI10-Questions!AJ10-Questions!AO10 -> -2.1 | E10: =Questions!D10+Questions!E10+Questions!H10+Questions!G10+Questions!L10+Questions!K10+Questions!N10-Questions!O10+Questions!P10+Questions!S10-Questions!R10+Questions!Z10+Questions!AB10+Questions!AD10+Questions!AE10+Questions!AG10+Questions!AN10 -> 0.2
A11: Pour ou contre les préliminaires | B11: =Questions!B11+Questions!Q11+Questions!AO11+Questions!AJ11+Questions!AH11+Questions!AG11+Questions!AC11 -> 0 | C11: =Questions!C11+Questions!G11+Questions!M11-Questions!O11-Questions!T11-Questions!X11+Questions!Z11+Questions!AM11-Questions!AL11+Questions!AK11 -> 1.4 | D11: =-Questions!B11-Questions!F11+Questions!J11-Questions!M11+Questions!R11+Questions!T11+Questions!U11+Questions!V11+Questions!X11+Questions!AA11-Questions!AE11+Questions!AF11-Questions!AG11-Questions!AH11+Questions!AI11-Questions!AJ11-Questions!AO11 -> -0.2 | E11: =Questions!D11+Questions!E11+Questions!H11+Questions!G11+Questions!L11+Questions!K11+Questions!N11-Questions!O11+Questions!P11+Questions!S11-Questions!R11+Questions!Z11+Questions!AB11+Questions!AD11+Questions!AE11+Questions!AG11+Questions!AN11 -> 0.2
A12: Pour ou contre la collapsologie | B12: =Questions!B12+Questions!Q12+Questions!AO12+Questions!AJ12+Questions!AH12+Questions!AG12+Questions!AC12 -> -0.1 | C12: =Questions!C12+Questions!G12+Questions!M12-Questions!O12-Questions!T12-Questions!X12+Questions!Z12+Questions!AM12-Questions!AL12+Questions!AK12 -> 0 | D12: =-Questions!B12-Questions!F12+Questions!J12-Questions!M12+Questions!R12+Questions!T12+Questions!U12+Questions!V12+Questions!X12+Questions!AA12-Questions!AE12+Questions!AF12-Questions!AG12-Questions!AH12+Questions!AI12-Questions!AJ12-Questions!AO12 -> 0.3 | E12: =Questions!D12+Questions!E12+Questions!H12+Questions!G12+Questions!L12+Questions!K12+Questions!N12-Questions!O12+Questions!P12+Questions!S12-Questions!R12+Questions!Z12+Questions!AB12+Questions!AD12+Questions!AE12+Questions!AG12+Questions!AN12 -> 0.7
A13: Pour ou contre le survivalisme | B13: =Questions!B13+Questions!Q13+Questions!AO13+Questions!AJ13+Questions!AH13+Questions!AG13+Questions!AC13 -> 0.2 | C13: =Questions!C13+Questions!G13+Questions!M13-Questions!O13-Questions!T13-Questions!X13+Questions!Z13+Questions!AM13-Questions!AL13+Questions!AK13 -> 0 | D13: =-Questions!B13-Questions!F13+Questions!J13-Questions!M13+Questions!R13+Questions!T13+Questions!U13+Questions!V13+Questions!X13+Questions!AA13-Questions!AE13+Questions!AF13-Questions!AG13-Questions!AH13+Questions!AI13-Questions!AJ13-Questions!AO13 -> 0.4 | E13: =Questions!D13+Questions!E13+Questions!H13+Questions!G13+Questions!L13+Questions!K13+Questions!N13-Questions!O13+Questions!P13+Questions!S13-Questions!R13+Questions!Z13+Questions!AB13+Questions!AD13+Questions!AE13+Questions!AG13+Questions!AN13 -> 0.2
... A195: Pour ou contre les parisiens | B195: =Questions!B195+Questions!Q195+Questions!AO195+Questions!AJ195+Questions!AH195+Questions!AG195+Questions!AC195 -> 0 | C195: =Questions!C195+Questions!G195+Questions!M195-Questions!O195-Questions!T195-Questions!X195+Questions!Z195+Questions!AM195-Questions!AL195+Questions!AK195 -> 0 | D195: =-Questions!B195-Questions!F195+Questions!J195-Questions!M195+Questions!R195+Questions!T195+Questions!U195+Questions!V195+Questions!X195+Questions!AA195-Questions!AE195+Questions!AF195-Questions!AG195-Questions!AH195+Questions!AI195-Questions!AJ195-Questions!AO195 -> 0 | E195: =Questions!D195+Questions!E195+Questions!H195+Questions!G195+Questions!L195+Questions!K195+Questions!N195-Questions!O195+Questions!P195+Questions!S195-Questions!R195+Questions!Z195+Questions!AB195+Questions!AD195+Questions!AE195+Questions!AG195+Questions!AN195 -> 0
